zerotrue/__init__.py
zerotrue/async_client.py
zerotrue/client.py
zerotrue/exceptions.py
zerotrue/http_client.py
zerotrue/py.typed
zerotrue/types.py
zerotrue/resources/__init__.py
zerotrue/resources/async_checks.py
zerotrue/resources/checks.py
zerotrue_sdk-1.2.0.dist-info/LICENSE
zerotrue_sdk-1.2.0.dist-info/METADATA
zerotrue_sdk-1.2.0.dist-info/WHEEL
zerotrue_sdk-1.2.0.dist-info/top_level.txt
zerotrue_sdk-1.2.0.dist-info/RECORD
