Metadata-Version: 2.1
Name: zerotrue-sdk
Version: 1.2.0
Summary: Official Python SDK for ZeroTrue AI Detection API - Detect AI-generated content in text, images, videos, and audio
Author-email: ZeroTrueLCC <support@zerotrue.ai>
License: MIT
Project-URL: Homepage, https://app.zerotrue.app
Project-URL: Documentation, https://app.zerotrue.app/docs
Project-URL: Repository, https://github.com/ZeroTrueLCC/sdk-python
Project-URL: Issues, https://github.com/ZeroTrueLCC/sdk-python/issues
Keywords: ai,detection,zerotrue,content-analysis,sdk
Classifier: Development Status :: 4 - Beta
Classifier: Intended Audience :: Developers
Classifier: License :: OSI Approved :: MIT License
Classifier: Programming Language :: Python :: 3
Classifier: Programming Language :: Python :: 3.8
Classifier: Programming Language :: Python :: 3.9
Classifier: Programming Language :: Python :: 3.10
Classifier: Programming Language :: Python :: 3.11
Classifier: Programming Language :: Python :: 3.12
Classifier: Programming Language :: Python :: 3.13
Classifier: Topic :: Software Development :: Libraries :: Python Modules
Classifier: Topic :: Scientific/Engineering :: Artificial Intelligence
Requires-Python: >=3.8
License-File: LICENSE
Requires-Dist: httpx>=0.28.1
Provides-Extra: dev
Requires-Dist: pytest>=7.4.0; extra == "dev"
Requires-Dist: pytest-asyncio>=0.21.0; extra == "dev"
Requires-Dist: pytest-cov>=4.1.0; extra == "dev"
Requires-Dist: black>=23.0.0; extra == "dev"
Requires-Dist: ruff>=0.1.0; extra == "dev"
Requires-Dist: mypy>=1.5.0; extra == "dev"
Requires-Dist: pre-commit>=3.5.0; extra == "dev"
